{
  "placeholderImages": [
    {
      "id": "hero-banner",
      "description": "Ciseaux et peigne de coiffeur",
      "imageUrl": "https://picsum.photos/seed/scissors/1920/1080",
      "imageHint": "scissors comb"
    },
    {
      "id": "younes-portrait",
      "description": "Portrait de Younes",
      "imageUrl": "https://picsum.photos/seed/younes/400/400",
      "imageHint": "male portrait"
    },
    {
      "id": "yacine-portrait",
      "description": "Portrait de Yacine",
      "imageUrl": "https://picsum.photos/seed/yacine/400/400",
      "imageHint": "male portrait"
    },
    {
      "id": "khudhur-portrait",
      "description": "Portrait de Khudhur",
      "imageUrl": "https://picsum.photos/seed/khudhur/400/400",
      "imageHint": "male portrait"
    }
  ]
}
